bmt_tools/WikiSearch.py
bmt_tools/__init__.py
bmt_tools/bmtMetric.py
bmt_tools/bmtURLTools.py
bmt_tools/data/IMDBMu.npy
bmt_tools/data/newIMDBMu.npy
bmt_tools-0.2.2.dist-info/DESCRIPTION.rst
bmt_tools-0.2.2.dist-info/METADATA
bmt_tools-0.2.2.dist-info/RECORD
bmt_tools-0.2.2.dist-info/WHEEL
bmt_tools-0.2.2.dist-info/metadata.json
bmt_tools-0.2.2.dist-info/top_level.txt
