Metadata-Version: 2.0
Name: bmt-tools
Version: 0.2.2
Summary: Tools for Bad Movie Twins
Home-page: http://github.com/patsmad/BMT/bmt_tools
Author: Patrick Smadbeck
Author-email: patrick@smadbeck.com
License: UNKNOWN
Platform: UNKNOWN
Requires-Dist: beautifulsoup4
Requires-Dist: numpy
Requires-Dist: requests
